doublethink/__init__.py
doublethink/cli.py
doublethink/orm.py
doublethink/rethinker.py
doublethink/services.py
doublethink-0.4.10.dist-info/METADATA
doublethink-0.4.10.dist-info/WHEEL
doublethink-0.4.10.dist-info/entry_points.txt
doublethink-0.4.10.dist-info/top_level.txt
doublethink-0.4.10.dist-info/RECORD
