Metadata-Version: 2.2
Name: doublethink
Version: 0.4.10
Summary: rethinkdb python library
Home-page: https://github.com/internetarchive/doublethink
Author: Noah Levitt
Author-email: Noah Levitt <nlevitt@archive.org>
Maintainer-email: Barbara Miller <barbara@archive.org>
License: license.txt
Project-URL: Homepage, https://github.com/internetarchive/doublethink
Project-URL: Issues, https://github.com/internetarchive/doublethink/issues
Classifier: Programming Language :: Python :: 3
Classifier: License :: OSI Approved :: Apache Software License
Classifier: Operating System :: OS Independent
Requires-Python: >=3.8
Requires-Dist: rethinkdb==2.4.9
Provides-Extra: test
Requires-Dist: pytest; extra == "test"
Dynamic: author
Dynamic: home-page
Dynamic: license
Dynamic: provides-extra
Dynamic: requires-dist
